kur/__init__.py
kur/__main__.py
kur/kurfile.py
kur/version.py
kur/backend/__init__.py
kur/backend/backend.py
kur/backend/keras_backend.py
kur/backend/pytorch_backend.py
kur/backend/pytorch/__init__.py
kur/backend/pytorch/modules.py
kur/containers/__init__.py
kur/containers/container.py
kur/containers/parsing_error.py
kur/containers/layers/__init__.py
kur/containers/layers/activation.py
kur/containers/layers/batchnorm.py
kur/containers/layers/convolution.py
kur/containers/layers/dense.py
kur/containers/layers/dropout.py
kur/containers/layers/embedding.py
kur/containers/layers/expand.py
kur/containers/layers/flatten.py
kur/containers/layers/layer.py
kur/containers/layers/merge.py
kur/containers/layers/output.py
kur/containers/layers/parallel.py
kur/containers/layers/placeholder.py
kur/containers/layers/pooling.py
kur/containers/layers/recurrent.py
kur/containers/layers/repeat.py
kur/containers/layers/reuse.py
kur/containers/layers/squeeze.py
kur/containers/layers/transpose.py
kur/containers/operators/__init__.py
kur/containers/operators/assertion.py
kur/containers/operators/container_group.py
kur/containers/operators/debug.py
kur/containers/operators/for_each.py
kur/containers/operators/for_loop.py
kur/containers/operators/meta.py
kur/containers/operators/operator.py
kur/engine/__init__.py
kur/engine/engine.py
kur/engine/jinja_engine.py
kur/engine/passthrough_engine.py
kur/loggers/__init__.py
kur/loggers/binary_logger.py
kur/loggers/logger.py
kur/loggers/persistent_logger.py
kur/loggers/statistic.py
kur/loss/__init__.py
kur/loss/categorical_crossentropy.py
kur/loss/ctc.py
kur/loss/loss.py
kur/loss/mean_squared_error.py
kur/model/__init__.py
kur/model/executor.py
kur/model/model.py
kur/model/hooks/__init__.py
kur/model/hooks/hooks.py
kur/model/hooks/kurhub_hook.py
kur/model/hooks/mnist_hook.py
kur/model/hooks/output_hook.py
kur/model/hooks/plot_hook.py
kur/model/hooks/slack_hook.py
kur-0.7.0.dist-info/DESCRIPTION.rst
kur-0.7.0.dist-info/METADATA
kur-0.7.0.dist-info/RECORD
kur-0.7.0.dist-info/WHEEL
kur-0.7.0.dist-info/entry_points.txt
kur-0.7.0.dist-info/metadata.json
kur-0.7.0.dist-info/top_level.txt
