Metadata-Version: 2.0
Name: kur
Version: 0.7.0
Summary: Descriptive deep learning
Home-page: https://github.com/deepgram/kur
Author: Adam Sypniewski
Author-email: adam@deepgram.com
License: Apache Software License (http://www.apache.org/licenses/LICENSE-2.0)
Keywords: deep learning
Platform: UNKNOWN
Requires-Dist: jinja2 (>=2.8)
Requires-Dist: keras (>=1.2.2)
Requires-Dist: matplotlib (>=1.5.3)
Requires-Dist: numpy (>=1.11.2)
Requires-Dist: pydub (>=0.16.6)
Requires-Dist: python-magic (>=0.4.12)
Requires-Dist: python-speech-features (>=0.4)
Requires-Dist: pyyaml (>=3.12)
Requires-Dist: scipy (>=0.18.1)
Requires-Dist: theano (>=0.8.2)
Requires-Dist: tqdm (>=4.10.0)
